pygmt/__init__.py
pygmt/_show_versions.py
pygmt/_typing.py
pygmt/alias.py
pygmt/conftest.py
pygmt/encodings.py
pygmt/enums.py
pygmt/exceptions.py
pygmt/figure.py
pygmt/io.py
pygmt/session_management.py
pygmt/sphinx_gallery.py
pygmt/clib/__init__.py
pygmt/clib/conversion.py
pygmt/clib/loading.py
pygmt/clib/session.py
pygmt/datasets/__init__.py
pygmt/datasets/earth_age.py
pygmt/datasets/earth_day.py
pygmt/datasets/earth_deflection.py
pygmt/datasets/earth_dist.py
pygmt/datasets/earth_free_air_anomaly.py
pygmt/datasets/earth_geoid.py
pygmt/datasets/earth_magnetic_anomaly.py
pygmt/datasets/earth_mask.py
pygmt/datasets/earth_mean_dynamic_topography.py
pygmt/datasets/earth_mean_sea_surface.py
pygmt/datasets/earth_night.py
pygmt/datasets/earth_relief.py
pygmt/datasets/earth_vertical_gravity_gradient.py
pygmt/datasets/load_remote_dataset.py
pygmt/datasets/mars_relief.py
pygmt/datasets/mercury_relief.py
pygmt/datasets/moon_relief.py
pygmt/datasets/pluto_relief.py
pygmt/datasets/samples.py
pygmt/datasets/tile_map.py
pygmt/datasets/venus_relief.py
pygmt/datatypes/__init__.py
pygmt/datatypes/dataset.py
pygmt/datatypes/grid.py
pygmt/datatypes/header.py
pygmt/datatypes/image.py
pygmt/helpers/__init__.py
pygmt/helpers/caching.py
pygmt/helpers/decorators.py
pygmt/helpers/tempfile.py
pygmt/helpers/testing.py
pygmt/helpers/utils.py
pygmt/helpers/validators.py
pygmt/params/__init__.py
pygmt/params/base.py
pygmt/params/box.py
pygmt/params/pattern.py
pygmt/src/__init__.py
pygmt/src/_common.py
pygmt/src/basemap.py
pygmt/src/binstats.py
pygmt/src/blockm.py
pygmt/src/coast.py
pygmt/src/colorbar.py
pygmt/src/config.py
pygmt/src/contour.py
pygmt/src/dimfilter.py
pygmt/src/filter1d.py
pygmt/src/grd2cpt.py
pygmt/src/grd2xyz.py
pygmt/src/grdclip.py
pygmt/src/grdcontour.py
pygmt/src/grdcut.py
pygmt/src/grdfill.py
pygmt/src/grdfilter.py
pygmt/src/grdgradient.py
pygmt/src/grdhisteq.py
pygmt/src/grdimage.py
pygmt/src/grdinfo.py
pygmt/src/grdlandmask.py
pygmt/src/grdproject.py
pygmt/src/grdsample.py
pygmt-0.17.0.dist-info/licenses/LICENSE.txt
pygmt-0.17.0.dist-info/METADATA
pygmt-0.17.0.dist-info/WHEEL
pygmt-0.17.0.dist-info/entry_points.txt
pygmt-0.17.0.dist-info/top_level.txt
pygmt-0.17.0.dist-info/RECORD
