Metadata-Version: 2.4
Name: pygmt
Version: 0.17.0
Summary: A Python interface for the Generic Mapping Tools
Author-email: The PyGMT Developers <pygmt.team@gmail.com>
License-Expression: BSD-3-Clause
Project-URL: Homepage, https://www.pygmt.org
Project-URL: Documentation, https://www.pygmt.org
Project-URL: Source Code, https://github.com/GenericMappingTools/pygmt
Project-URL: Changelog, https://www.pygmt.org/latest/changes.html
Project-URL: Issue Tracker, https://github.com/GenericMappingTools/pygmt/issues
Keywords: cartography,geodesy,geology,geophysics,geospatial,oceanography,seismology
Classifier: Development Status :: 4 - Beta
Classifier: Intended Audience :: Science/Research
Classifier: Intended Audience :: Developers
Classifier: Intended Audience :: Education
Classifier: Topic :: Scientific/Engineering
Classifier: Topic :: Software Development :: Libraries
Classifier: Operating System :: MacOS
Classifier: Operating System :: Microsoft :: Windows
Classifier: Operating System :: POSIX
Classifier: Operating System :: Unix
Classifier: Programming Language :: Python :: 3.11
Classifier: Programming Language :: Python :: 3.12
Classifier: Programming Language :: Python :: 3.13
Requires-Python: >=3.11
License-File: LICENSE.txt
Requires-Dist: numpy>=1.26
Requires-Dist: pandas>=2.2
Requires-Dist: xarray>=2023.10
Requires-Dist: packaging>=24.2
Provides-Extra: all
Requires-Dist: contextily>=1.5; extra == "all"
Requires-Dist: geopandas>=1.0; extra == "all"
Requires-Dist: IPython; extra == "all"
Requires-Dist: pyarrow>=16; extra == "all"
Requires-Dist: rioxarray; extra == "all"
Dynamic: license-file
